{
  "verifications": [
    {
      "claim_id": "C1",
      "status": "verified",
      "evidence_ids": [
        "E:note:row544481:1"
      ],
      "rationale": "The candidate evidence explicitly states the patient is a 'morbidly obese female'."
    },
    {
      "claim_id": "C2",
      "status": "unsupported",
      "evidence_ids": [],
      "rationale": "The candidates mention a total knee replacement and kidney disease, but do not explicitly state a history of chronic left knee pain."
    },
    {
      "claim_id": "C3",
      "status": "unsupported",
      "evidence_ids": [],
      "rationale": "The evidence only indicates an 'ELECTIVE' encounter but does not specify that a total left knee replacement was performed."
    },
    {
      "claim_id": "C4",
      "status": "verified",
      "evidence_ids": [
        "E:note:row544481:3"
      ],
      "rationale": "The evidence explicitly states that the post op patient was given morphine."
    },
    {
      "claim_id": "C5",
      "status": "verified",
      "evidence_ids": [
        "E:cond:12"
      ],
      "rationale": "The candidate evidence explicitly lists a diagnosis of iatrogenic hypotension."
    },
    {
      "claim_id": "C6",
      "status": "unsupported",
      "evidence_ids": [],
      "rationale": "No candidate evidence found in EHR."
    },
    {
      "claim_id": "C7",
      "status": "unsupported",
      "evidence_ids": [],
      "rationale": "No candidate evidence found in EHR."
    },
    {
      "claim_id": "C8",
      "status": "unsupported",
      "evidence_ids": [],
      "rationale": "No candidate evidence found in EHR."
    },
    {
      "claim_id": "C9",
      "status": "unsupported",
      "evidence_ids": [],
      "rationale": "The candidates mention a total knee replacement and kidney disease, but do not explicitly document a diagnosis of chronic back and knee pain."
    },
    {
      "claim_id": "C10",
      "status": "unsupported",
      "evidence_ids": [],
      "rationale": "No candidate evidence found in EHR."
    },
    {
      "claim_id": "C11",
      "status": "unsupported",
      "evidence_ids": [],
      "rationale": "No candidate evidence found in EHR."
    },
    {
      "claim_id": "C12",
      "status": "unsupported",
      "evidence_ids": [],
      "rationale": "The candidate evidence describes a kidney disease condition and does not mention medication or fentanyl."
    },
    {
      "claim_id": "C13",
      "status": "unsupported",
      "evidence_ids": [],
      "rationale": "No candidate evidence found in EHR."
    },
    {
      "claim_id": "C14",
      "status": "unsupported",
      "evidence_ids": [],
      "rationale": "No candidate evidence found in EHR."
    },
    {
      "claim_id": "C15",
      "status": "unsupported",
      "evidence_ids": [],
      "rationale": "No candidate evidence found in EHR."
    },
    {
      "claim_id": "C16",
      "status": "unsupported",
      "evidence_ids": [],
      "rationale": "The candidate evidence describes a procedure complication (hemorrhage) and does not mention PCA or medication administration."
    },
    {
      "claim_id": "C17",
      "status": "unsupported",
      "evidence_ids": [],
      "rationale": "No candidate evidence found in EHR."
    },
    {
      "claim_id": "C18",
      "status": "unsupported",
      "evidence_ids": [],
      "rationale": "No candidate evidence found in EHR."
    },
    {
      "claim_id": "C19",
      "status": "unsupported",
      "evidence_ids": [],
      "rationale": "No candidate evidence found in EHR."
    },
    {
      "claim_id": "C20",
      "status": "unsupported",
      "evidence_ids": [],
      "rationale": "No candidate evidence found in EHR."
    },
    {
      "claim_id": "C21",
      "status": "unsupported",
      "evidence_ids": [],
      "rationale": "The provided candidates contain information about conditions and a procedure, but no lab results for hematocrit (hct)."
    },
    {
      "claim_id": "C22",
      "status": "unsupported",
      "evidence_ids": [],
      "rationale": "While E:proc:4 confirms a transfusion of packed cells, it does not specify the quantity (2 units) required to verify the claim."
    },
    {
      "claim_id": "C23",
      "status": "unsupported",
      "evidence_ids": [],
      "rationale": "The candidates list a transfusion procedure but provide no lab results for gtt levels."
    },
    {
      "claim_id": "C24",
      "status": "unsupported",
      "evidence_ids": [],
      "rationale": "The evidence shows a past procedure of transfusion, but does not indicate a plan to repeat it."
    }
  ]
}