{
  "case_id": "mimic-50004-131407-447958",
  "sections": {
    "hpi": [],
    "active_problems": [
      {
        "text": "Complications of transplanted kidney (2141-04-13)",
        "evidence_ids": [
          "E:cond:1"
        ]
      },
      {
        "text": "Systemic inflammatory response syndrome due to noninfectious process with acute organ dysfunction (2141-04-13)",
        "evidence_ids": [
          "E:cond:2"
        ]
      },
      {
        "text": "Acute respiratory failure (2141-04-13)",
        "evidence_ids": [
          "E:cond:3"
        ]
      },
      {
        "text": "Acute kidney failure with lesion of tubular necrosis (2141-04-13)",
        "evidence_ids": [
          "E:cond:4"
        ]
      },
      {
        "text": "Acute and subacute necrosis of liver (2141-04-13)",
        "evidence_ids": [
          "E:cond:5"
        ]
      },
      {
        "text": "Other malignant lymphomas, unspecified site, extranodal and solid organ sites (2141-04-13)",
        "evidence_ids": [
          "E:cond:6"
        ]
      },
      {
        "text": "Acidosis (2141-04-13)",
        "evidence_ids": [
          "E:cond:7"
        ]
      },
      {
        "text": "Hyposmolality and/or hyponatremia (2141-04-13)",
        "evidence_ids": [
          "E:cond:8"
        ]
      },
      {
        "text": "Acquired coagulation factor deficiency (2141-04-13)",
        "evidence_ids": [
          "E:cond:9"
        ]
      },
      {
        "text": "Acute posthemorrhagic anemia (2141-04-13)",
        "evidence_ids": [
          "E:cond:10"
        ]
      },
      {
        "text": "Hematemesis (2141-04-13)",
        "evidence_ids": [
          "E:cond:11"
        ]
      },
      {
        "text": "Hypertrophy (benign) of prostate without urinary obstruction and other lower urinary tract symptom (LUTS) (2141-04-13)",
        "evidence_ids": [
          "E:cond:12"
        ]
      },
      {
        "text": "Thrombocytopenia, unspecified (2141-04-13)",
        "evidence_ids": [
          "E:cond:13"
        ]
      },
      {
        "text": "Other specified hypoglycemia (2141-04-13)",
        "evidence_ids": [
          "E:cond:14"
        ]
      },
      {
        "text": "Nephritis and nephropathy, not specified as acute or chronic, with unspecified pathological lesion in kidney (2141-04-13)",
        "evidence_ids": [
          "E:cond:15"
        ]
      },
      {
        "text": "Other shock without mention of trauma (2141-04-13)",
        "evidence_ids": [
          "E:cond:16"
        ]
      },
      {
        "text": "Unspecified essential hypertension (2141-04-13)",
        "evidence_ids": [
          "E:cond:17"
        ]
      },
      {
        "text": "Procedure: Laparoscopy (2141-04-13)",
        "evidence_ids": [
          "E:proc:1"
        ]
      },
      {
        "text": "Procedure: Biopsy of lymphatic structure (2141-04-13)",
        "evidence_ids": [
          "E:proc:2"
        ]
      },
      {
        "text": "Procedure: Biopsy of bone marrow (2141-04-13)",
        "evidence_ids": [
          "E:proc:3"
        ]
      },
      {
        "text": "Procedure: Hemodialysis (2141-04-13)",
        "evidence_ids": [
          "E:proc:4"
        ]
      },
      {
        "text": "Procedure: Continuous invasive mechanical ventilation for less than 96 consecutive hours (2141-04-13)",
        "evidence_ids": [
          "E:proc:5"
        ]
      },
      {
        "text": "has history of: kidney transplant",
        "evidence_ids": [
          "E:note:row447958:1"
        ]
      },
      {
        "text": "has diagnosis: AG acidosis",
        "evidence_ids": [
          "E:note:row447958:6"
        ]
      },
      {
        "text": "plan to: Considering Lymph node biopsy",
        "evidence_ids": [
          "E:note:row447958:19"
        ]
      }
    ],
    "medications": [
      {
        "text": "was given: Zosyn",
        "evidence_ids": [
          "E:note:row447958:3"
        ]
      },
      {
        "text": "was given: tylenol 1 gm",
        "evidence_ids": [
          "E:note:row447958:8"
        ]
      },
      {
        "text": "was given: vanc/cefepime",
        "evidence_ids": [
          "E:note:row447958:8"
        ]
      },
      {
        "text": "received: 4L of NS",
        "evidence_ids": [
          "E:note:row447958:9"
        ]
      },
      {
        "text": "takes medication: cyclosporine 70 po",
        "evidence_ids": [
          "E:note:row447958:22"
        ]
      }
    ],
    "labs": [
      {
        "text": "lab result: lactate of 7.5",
        "evidence_ids": [
          "E:note:row447958:6"
        ]
      },
      {
        "text": "lab result: LDH of 2635",
        "evidence_ids": [
          "E:note:row447958:6"
        ]
      },
      {
        "text": "lab result: leukocytosis with left shift",
        "evidence_ids": [
          "E:note:row447958:7"
        ]
      },
      {
        "text": "lab result: lactate came down to 5.4",
        "evidence_ids": [
          "E:note:row447958:10"
        ]
      },
      {
        "text": "lab result: WBC 14.5",
        "evidence_ids": [
          "E:note:row447958:14"
        ]
      },
      {
        "text": "lab result: Lactate down to 4.5",
        "evidence_ids": [
          "E:note:row447958:15"
        ]
      },
      {
        "text": "lab result: CMV/EBV labs sent to eval",
        "evidence_ids": [
          "E:note:row447958:17"
        ]
      }
    ],
    "vitals": [
      {
        "text": "vital sign: 99.2",
        "evidence_ids": [
          "E:note:row447958:5"
        ]
      },
      {
        "text": "vital sign: 101",
        "evidence_ids": [
          "E:note:row447958:5"
        ]
      },
      {
        "text": "vital sign: 18",
        "evidence_ids": [
          "E:note:row447958:5"
        ]
      },
      {
        "text": "vital sign: 136/83",
        "evidence_ids": [
          "E:note:row447958:5"
        ]
      },
      {
        "text": "vital sign: 97% on RA",
        "evidence_ids": [
          "E:note:row447958:5"
        ]
      },
      {
        "text": "vital sign: fever to 102.6",
        "evidence_ids": [
          "E:note:row447958:8"
        ]
      },
      {
        "text": "vital sign: Afebrile",
        "evidence_ids": [
          "E:note:row447958:12",
          "E:note:row447958:16"
        ]
      },
      {
        "text": "vital sign: sats 95-98% on RA",
        "evidence_ids": [
          "E:note:row447958:23"
        ]
      }
    ],
    "plan": []
  }
}