{
  "claims": [
    {
      "claim_id": "C1",
      "type": "diagnosis",
      "subject": "patient",
      "predicate": "has diagnosis",
      "value": "Respiratory failure, acute (not ARDS/[**Doctor Last Name 2**])",
      "time_ref": null,
      "source_span": "row540683#0"
    },
    {
      "claim_id": "C2",
      "type": "procedure",
      "subject": "patient",
      "predicate": "received",
      "value": "CMV",
      "time_ref": null,
      "source_span": "row540683#1"
    },
    {
      "claim_id": "C3",
      "type": "vital",
      "subject": "patient",
      "predicate": "lab result",
      "value": "Sat maintain>99%",
      "time_ref": null,
      "source_span": "row540683#1"
    },
    {
      "claim_id": "C4",
      "type": "diagnosis",
      "subject": "patient",
      "predicate": "has finding",
      "value": "LS rhonchus, diminish with crackles in bases",
      "time_ref": null,
      "source_span": "row540683#1"
    },
    {
      "claim_id": "C5",
      "type": "procedure",
      "subject": "patient",
      "predicate": "plan to",
      "value": "Start diuresis with lasix gtt",
      "time_ref": null,
      "source_span": "row540683#2"
    },
    {
      "claim_id": "C6",
      "type": "procedure",
      "subject": "patient",
      "predicate": "plan to",
      "value": "Weaning to cpap",
      "time_ref": null,
      "source_span": "row540683#2"
    },
    {
      "claim_id": "C7",
      "type": "vital",
      "subject": "patient",
      "predicate": "lab result",
      "value": "tachpneas 40s on cpap even with IPS 20",
      "time_ref": null,
      "source_span": "row540683#3"
    },
    {
      "claim_id": "C8",
      "type": "procedure",
      "subject": "patient",
      "predicate": "received",
      "value": "Placed back to CMV",
      "time_ref": null,
      "source_span": "row540683#3"
    },
    {
      "claim_id": "C9",
      "type": "diagnosis",
      "subject": "patient",
      "predicate": "has diagnosis",
      "value": "Liver function abnormalities",
      "time_ref": null,
      "source_span": "row540683#5"
    },
    {
      "claim_id": "C10",
      "type": "diagnosis",
      "subject": "patient",
      "predicate": "has finding",
      "value": "Patient body and both eyes are still jaundiced",
      "time_ref": null,
      "source_span": "row540683#6"
    },
    {
      "claim_id": "C11",
      "type": "lab",
      "subject": "patient",
      "predicate": "lab result",
      "value": "Liver function studies remain elevated",
      "time_ref": null,
      "source_span": "row540683#6"
    },
    {
      "claim_id": "C12",
      "type": "lab",
      "subject": "patient",
      "predicate": "lab result",
      "value": "Marginal drop in bilirubin",
      "time_ref": null,
      "source_span": "row540683#6"
    },
    {
      "claim_id": "C13",
      "type": "procedure",
      "subject": "patient",
      "predicate": "has",
      "value": "Choly-tube draining clear bile to gravity",
      "time_ref": null,
      "source_span": "row540683#6"
    },
    {
      "claim_id": "C14",
      "type": "plan",
      "subject": "patient",
      "predicate": "plan to",
      "value": "NPO",
      "time_ref": null,
      "source_span": "row540683#7"
    },
    {
      "claim_id": "C15",
      "type": "medication",
      "subject": "patient",
      "predicate": "takes medication",
      "value": "TPN",
      "time_ref": null,
      "source_span": "row540683#7"
    },
    {
      "claim_id": "C16",
      "type": "diagnosis",
      "subject": "patient",
      "predicate": "has diagnosis",
      "value": "ABDOMEN WOUND",
      "time_ref": null,
      "source_span": "row540683#9"
    },
    {
      "claim_id": "C17",
      "type": "diagnosis",
      "subject": "patient",
      "predicate": "has finding",
      "value": "Abdomen open ->, adaptic over liver/below LLQ, wound bed beefy red",
      "time_ref": null,
      "source_span": "row540683#10"
    },
    {
      "claim_id": "C18",
      "type": "diagnosis",
      "subject": "patient",
      "predicate": "has finding",
      "value": "Edges with mod amt yellow fibrin/exudate",
      "time_ref": null,
      "source_span": "row540683#11"
    },
    {
      "claim_id": "C19",
      "type": "procedure",
      "subject": "patient",
      "predicate": "has",
      "value": "Draining catheter at fistula site->golden liquid matter to low sxn",
      "time_ref": null,
      "source_span": "row540683#11"
    },
    {
      "claim_id": "C20",
      "type": "medication",
      "subject": "patient",
      "predicate": "plan to",
      "value": "pre medicate with versed and fentanyl ivp pre-procedure",
      "time_ref": null,
      "source_span": "row540683#12"
    },
    {
      "claim_id": "C21",
      "type": "diagnosis",
      "subject": "patient",
      "predicate": "has diagnosis",
      "value": "Fever (Hyperthermia, Pyrexia, not Fever of Unknown Origin)",
      "time_ref": null,
      "source_span": "row540683#15"
    },
    {
      "claim_id": "C22",
      "type": "vital",
      "subject": "patient",
      "predicate": "lab result",
      "value": "Con t low grade temp",
      "time_ref": null,
      "source_span": "row540683#16"
    },
    {
      "claim_id": "C23",
      "type": "medication",
      "subject": "patient",
      "predicate": "takes medication",
      "value": "vancomycin",
      "time_ref": null,
      "source_span": "row540683#17"
    },
    {
      "claim_id": "C24",
      "type": "medication",
      "subject": "patient",
      "predicate": "takes medication",
      "value": "zosyn",
      "time_ref": null,
      "source_span": "row540683#17"
    },
    {
      "claim_id": "C25",
      "type": "medication",
      "subject": "patient",
      "predicate": "takes medication",
      "value": "diflucan",
      "time_ref": null,
      "source_span": "row540683#17"
    },
    {
      "claim_id": "C26",
      "type": "medication",
      "subject": "patient",
      "predicate": "takes medication",
      "value": "bactrim",
      "time_ref": "today",
      "source_span": "row540683#17"
    },
    {
      "claim_id": "C27",
      "type": "lab",
      "subject": "patient",
      "predicate": "lab result",
      "value": "positive sputum cx",
      "time_ref": "9-25",
      "source_span": "row540683#17"
    },
    {
      "claim_id": "C28",
      "type": "lab",
      "subject": "patient",
      "predicate": "lab result",
      "value": "Wbc trending down marginally today",
      "time_ref": "today",
      "source_span": "row540683#18"
    },
    {
      "claim_id": "C29",
      "type": "diagnosis",
      "subject": "patient",
      "predicate": "has diagnosis",
      "value": "Acute Pain--sedation",
      "time_ref": null,
      "source_span": "row540683#20"
    },
    {
      "claim_id": "C30",
      "type": "medication",
      "subject": "patient",
      "predicate": "takes medication",
      "value": "fentanyl and versed gtt",
      "time_ref": null,
      "source_span": "row540683#21"
    },
    {
      "claim_id": "C31",
      "type": "medication",
      "subject": "patient",
      "predicate": "plan to",
      "value": "D c versed gtt-started on prn iv",
      "time_ref": null,
      "source_span": "row540683#22"
    },
    {
      "claim_id": "C32",
      "type": "medication",
      "subject": "patient",
      "predicate": "plan to",
      "value": "Wean fentanyl gtt as tolerate",
      "time_ref": null,
      "source_span": "row540683#22"
    },
    {
      "claim_id": "C33",
      "type": "diagnosis",
      "subject": "patient",
      "predicate": "has diagnosis",
      "value": "Tachycardia, Other",
      "time_ref": null,
      "source_span": "row540683#25"
    },
    {
      "claim_id": "C34",
      "type": "vital",
      "subject": "patient",
      "predicate": "lab result",
      "value": "ST 100s-110s",
      "time_ref": null,
      "source_span": "row540683#26"
    },
    {
      "claim_id": "C35",
      "type": "vital",
      "subject": "patient",
      "predicate": "lab result",
      "value": "SBP 100s-130s",
      "time_ref": null,
      "source_span": "row540683#26"
    },
    {
      "claim_id": "C36",
      "type": "diagnosis",
      "subject": "patient",
      "predicate": "has diagnosis",
      "value": "Impaired Physical Mobility",
      "time_ref": null,
      "source_span": "row540683#30"
    },
    {
      "claim_id": "C37",
      "type": "diagnosis",
      "subject": "patient",
      "predicate": "has finding",
      "value": "Patient bodily very edematous and stiff",
      "time_ref": null,
      "source_span": "row540683#31"
    }
  ]
}