{
  "passed": false,
  "violations": [
    {
      "sentence": "Current medications include:",
      "rule": "missing_citation",
      "detail": "Sentence has no [E:...] citation."
    }
  ],
  "sentence_count": 25,
  "cited_evidence_ids": [
    "E:cond:1",
    "E:cond:10",
    "E:cond:11",
    "E:cond:12",
    "E:cond:13",
    "E:cond:14",
    "E:cond:15",
    "E:cond:16",
    "E:cond:17",
    "E:cond:18",
    "E:cond:2",
    "E:cond:3",
    "E:cond:4",
    "E:cond:5",
    "E:cond:6",
    "E:cond:7",
    "E:cond:8",
    "E:cond:9",
    "E:note:row1282:10",
    "E:note:row1282:106",
    "E:note:row1282:107",
    "E:note:row1282:110",
    "E:note:row1282:111",
    "E:note:row1282:112",
    "E:note:row1282:113",
    "E:note:row1282:114",
    "E:note:row1282:115",
    "E:note:row1282:21",
    "E:note:row1282:22",
    "E:note:row1282:23",
    "E:note:row1282:28",
    "E:note:row1282:32",
    "E:note:row1282:33",
    "E:note:row1282:37",
    "E:note:row1282:40",
    "E:note:row1282:47",
    "E:note:row1282:48",
    "E:note:row1282:49",
    "E:note:row1282:57",
    "E:note:row1282:61",
    "E:note:row1282:63",
    "E:note:row1282:66",
    "E:note:row1282:70",
    "E:note:row1282:82",
    "E:note:row1282:83",
    "E:note:row1282:84",
    "E:note:row1282:89",
    "E:note:row1282:90",
    "E:note:row1282:91",
    "E:note:row1282:97",
    "E:note:row1282:98",
    "E:proc:1",
    "E:proc:2",
    "E:proc:3",
    "E:proc:4",
    "E:proc:5"
  ]
}